<?xml version="1.0" encoding="UTF-8" standalone="no"?>
<b:Sources xmlns:b="http://schemas.openxmlformats.org/officeDocument/2006/bibliography" xmlns="http://schemas.openxmlformats.org/officeDocument/2006/bibliography" SelectedStyle="">
    <b:Source>
        <b:LCID>1033</b:LCID>
        <b:Year>2017</b:Year>
        <b:Volume>44</b:Volume>
        <b:BIBTEX_Entry>article</b:BIBTEX_Entry>
        <b:SourceType>JournalArticle</b:SourceType>
        <b:Title>Sin Stocks Revisited: Resolving the Sin Stock Anomaly</b:Title>
        <b:Tag>blitz</b:Tag>
        <b:Author>
            <b:Author>
                <b:NameList>
                    <b:Person>
                        <b:Last>Blitz</b:Last>
                        <b:First>David</b:First>
                    </b:Person>
                    <b:Person>
                        <b:Last>Fabozzi</b:Last>
                        <b:Middle>J.</b:Middle>
                        <b:First>Frank</b:First>
                    </b:Person>
                </b:NameList>
            </b:Author>
        </b:Author>
        <b:Pages>105-111</b:Pages>
        <b:JournalName>Journal of Portfolio Management</b:JournalName>
        <b:Number>1</b:Number>
    </b:Source>
    <b:Source>
        <b:Year>2020</b:Year>
        <b:Volume>33</b:Volume>
        <b:BIBTEX_Entry>article</b:BIBTEX_Entry>
        <b:SourceType>JournalArticle</b:SourceType>
        <b:Title>Hedging climate change news</b:Title>
        <b:Tag>engle2020</b:Tag>
        <b:Publisher>Oxford University Press</b:Publisher>
        <b:Author>
            <b:Author>
                <b:NameList>
                    <b:Person>
                        <b:Last>Engle</b:Last>
                        <b:Middle>F.</b:Middle>
                        <b:First>Robert</b:First>
                    </b:Person>
                    <b:Person>
                        <b:Last>Giglio</b:Last>
                        <b:First>Stefano</b:First>
                    </b:Person>
                    <b:Person>
                        <b:Last>Kelly</b:Last>
                        <b:First>Bryan</b:First>
                    </b:Person>
                    <b:Person>
                        <b:Last>Lee</b:Last>
                        <b:First>Heebum</b:First>
                    </b:Person>
                    <b:Person>
                        <b:Last>Stroebel</b:Last>
                        <b:First>Johannes</b:First>
                    </b:Person>
                </b:NameList>
            </b:Author>
        </b:Author>
        <b:Pages>1184–1216</b:Pages>
        <b:JournalName>The Review of Financial Studies</b:JournalName>
        <b:Number>3</b:Number>
    </b:Source>
    <b:Source>
        <b:Year>2019</b:Year>
        <b:Volume>208</b:Volume>
        <b:BIBTEX_Entry>article</b:BIBTEX_Entry>
        <b:SourceType>JournalArticle</b:SourceType>
        <b:Title>Climate risks and market efficiency</b:Title>
        <b:Tag>hong2019</b:Tag>
        <b:Publisher>Elsevier</b:Publisher>
        <b:Author>
            <b:Author>
                <b:NameList>
                    <b:Person>
                        <b:Last>Hong</b:Last>
                        <b:First>Harrison</b:First>
                    </b:Person>
                    <b:Person>
                        <b:Last>Li</b:Last>
                        <b:Middle>Weikai</b:Middle>
                        <b:First>Frank</b:First>
                    </b:Person>
                    <b:Person>
                        <b:Last>Xu</b:Last>
                        <b:First>Jiangmin</b:First>
                    </b:Person>
                </b:NameList>
            </b:Author>
        </b:Author>
        <b:Pages>265–281</b:Pages>
        <b:JournalName>Journal of Econometrics</b:JournalName>
        <b:Number>1</b:Number>
    </b:Source>
    <b:Source>
        <b:Year>2020</b:Year>
        <b:BIBTEX_Entry>article</b:BIBTEX_Entry>
        <b:SourceType>JournalArticle</b:SourceType>
        <b:Title>A theory of socially responsible investment</b:Title>
        <b:Tag>oehmke2020</b:Tag>
        <b:Author>
            <b:Author>
                <b:NameList>
                    <b:Person>
                        <b:Last>Oehmke</b:Last>
                        <b:First>Martin</b:First>
                    </b:Person>
                    <b:Person>
                        <b:Last>Opp</b:Last>
                        <b:Middle>M.</b:Middle>
                        <b:First>Marcus</b:First>
                    </b:Person>
                </b:NameList>
            </b:Author>
        </b:Author>
        <b:JournalName>CEPR Discussion Paper No. DP14351</b:JournalName>
    </b:Source>
    <b:Source>
        <b:Year>2011</b:Year>
        <b:Volume>101</b:Volume>
        <b:BIBTEX_Entry>article</b:BIBTEX_Entry>
        <b:SourceType>JournalArticle</b:SourceType>
        <b:Title>Does the stock market fully value intangibles? Employee satisfaction and equity prices</b:Title>
        <b:Tag>edmans2011</b:Tag>
        <b:Publisher>Elsevier</b:Publisher>
        <b:Author>
            <b:Author>
                <b:NameList>
                    <b:Person>
                        <b:Last>Edmans</b:Last>
                        <b:First>Alex</b:First>
                    </b:Person>
                </b:NameList>
            </b:Author>
        </b:Author>
        <b:Pages>621–640</b:Pages>
        <b:JournalName>Journal of Financial economics</b:JournalName>
        <b:Number>3</b:Number>
    </b:Source>
    <b:Source>
        <b:Year>2018</b:Year>
        <b:BIBTEX_Entry>article</b:BIBTEX_Entry>
        <b:SourceType>JournalArticle</b:SourceType>
        <b:Title>The Price of Ignoring ESG Risks</b:Title>
        <b:Tag>glossner2018</b:Tag>
        <b:Author>
            <b:Author>
                <b:NameList>
                    <b:Person>
                        <b:Last>Gloßner</b:Last>
                        <b:First>Simon</b:First>
                    </b:Person>
                </b:NameList>
            </b:Author>
        </b:Author>
        <b:JournalName>Socially Responsible Investment eJournal</b:JournalName>
    </b:Source>
    <b:Source>
        <b:Year>2015</b:Year>
        <b:BIBTEX_Entry>article</b:BIBTEX_Entry>
        <b:SourceType>JournalArticle</b:SourceType>
        <b:Title>Climate change and firm valuation: Evidence from a quasi-natural experiment</b:Title>
        <b:Tag>krueger2015</b:Tag>
        <b:Author>
            <b:Author>
                <b:NameList>
                    <b:Person>
                        <b:Last>Krueger</b:Last>
                        <b:First>Philipp</b:First>
                    </b:Person>
                </b:NameList>
            </b:Author>
        </b:Author>
        <b:JournalName>Swiss Finance Institute Research Paper</b:JournalName>
        <b:Number>15-40</b:Number>
    </b:Source>
    <b:Source>
        <b:Year>2016</b:Year>
        <b:Volume>52</b:Volume>
        <b:BIBTEX_Entry>article</b:BIBTEX_Entry>
        <b:SourceType>JournalArticle</b:SourceType>
        <b:Title>Corporate social responsibility and financial performance: A non-linear and disaggregated approach</b:Title>
        <b:Tag>nollet2016</b:Tag>
        <b:Publisher>Elsevier</b:Publisher>
        <b:Author>
            <b:Author>
                <b:NameList>
                    <b:Person>
                        <b:Last>Nollet</b:Last>
                        <b:First>Joscha</b:First>
                    </b:Person>
                    <b:Person>
                        <b:Last>Filis</b:Last>
                        <b:First>George</b:First>
                    </b:Person>
                    <b:Person>
                        <b:Last>Mitrokostas</b:Last>
                        <b:First>Evangelos</b:First>
                    </b:Person>
                </b:NameList>
            </b:Author>
        </b:Author>
        <b:Pages>400–407</b:Pages>
        <b:JournalName>Economic Modelling</b:JournalName>
    </b:Source>
    <b:Source>
        <b:Year>2015</b:Year>
        <b:Volume>28</b:Volume>
        <b:BIBTEX_Entry>article</b:BIBTEX_Entry>
        <b:SourceType>JournalArticle</b:SourceType>
        <b:Title>Active ownership</b:Title>
        <b:Tag>dimson2015</b:Tag>
        <b:Publisher>Oxford University Press</b:Publisher>
        <b:Author>
            <b:Author>
                <b:NameList>
                    <b:Person>
                        <b:Last>Dimson</b:Last>
                        <b:First>Elroy</b:First>
                    </b:Person>
                    <b:Person>
                        <b:Last>Karakaş</b:Last>
                        <b:First>Oğuzhan</b:First>
                    </b:Person>
                    <b:Person>
                        <b:Last>Li</b:Last>
                        <b:First>Xi</b:First>
                    </b:Person>
                </b:NameList>
            </b:Author>
        </b:Author>
        <b:Pages>3225–3268</b:Pages>
        <b:JournalName>The Review of Financial Studies</b:JournalName>
        <b:Number>12</b:Number>
    </b:Source>
    <b:Source>
        <b:Year>2019</b:Year>
        <b:Volume>157</b:Volume>
        <b:BIBTEX_Entry>article</b:BIBTEX_Entry>
        <b:SourceType>JournalArticle</b:SourceType>
        <b:Title>Every Little Helps? ESG News and Stock Market Reaction</b:Title>
        <b:Tag>capelle2019</b:Tag>
        <b:Author>
            <b:Author>
                <b:NameList>
                    <b:Person>
                        <b:Last>Capelle-Blanchard</b:Last>
                        <b:First>Gunther</b:First>
                    </b:Person>
                    <b:Person>
                        <b:Last>Petit</b:Last>
                        <b:First>Aurelien</b:First>
                    </b:Person>
                </b:NameList>
            </b:Author>
        </b:Author>
        <b:Pages>543–565</b:Pages>
        <b:JournalName>Journal of Business Ethics</b:JournalName>
    </b:Source>
    <b:Source>
        <b:Year>2019</b:Year>
        <b:Volume>98</b:Volume>
        <b:BIBTEX_Entry>article</b:BIBTEX_Entry>
        <b:SourceType>JournalArticle</b:SourceType>
        <b:Title>The effect of pro-environmental preferences on bond prices: Evidence from green bonds</b:Title>
        <b:Tag>zerbib2019bond</b:Tag>
        <b:Publisher>Elsevier</b:Publisher>
        <b:Author>
            <b:Author>
                <b:NameList>
                    <b:Person>
                        <b:Last>Zerbib</b:Last>
                        <b:Middle>David</b:Middle>
                        <b:First>Olivier</b:First>
                    </b:Person>
                </b:NameList>
            </b:Author>
        </b:Author>
        <b:Pages>39–60</b:Pages>
        <b:JournalName>Journal of Banking &amp; Finance</b:JournalName>
    </b:Source>
    <b:Source>
        <b:Year>2019</b:Year>
        <b:BIBTEX_Entry>article</b:BIBTEX_Entry>
        <b:SourceType>JournalArticle</b:SourceType>
        <b:Title>The bond market benefits of corporate social capital</b:Title>
        <b:Tag>amiraslani2019</b:Tag>
        <b:Author>
            <b:Author>
                <b:NameList>
                    <b:Person>
                        <b:Last>Amiraslani</b:Last>
                        <b:First>Hami</b:First>
                    </b:Person>
                    <b:Person>
                        <b:Last>Lins</b:Last>
                        <b:Middle>V.</b:Middle>
                        <b:First>Karl</b:First>
                    </b:Person>
                    <b:Person>
                        <b:Last>Servaes</b:Last>
                        <b:First>Henri</b:First>
                    </b:Person>
                    <b:Person>
                        <b:Last>Tamayo</b:Last>
                        <b:First>Ane</b:First>
                    </b:Person>
                </b:NameList>
            </b:Author>
        </b:Author>
        <b:JournalName>European Corporate Governance Institute (ECGI)-Finance Working Paper</b:JournalName>
        <b:Number>535</b:Number>
    </b:Source>
    <b:Source>
        <b:Year>2017</b:Year>
        <b:Volume>72</b:Volume>
        <b:BIBTEX_Entry>article</b:BIBTEX_Entry>
        <b:SourceType>JournalArticle</b:SourceType>
        <b:Title>Why do investors hold socially responsible mutual funds?</b:Title>
        <b:Tag>riedl2017</b:Tag>
        <b:Publisher>Wiley Online Library</b:Publisher>
        <b:Author>
            <b:Author>
                <b:NameList>
                    <b:Person>
                        <b:Last>Riedl</b:Last>
                        <b:First>Arno</b:First>
                    </b:Person>
                    <b:Person>
                        <b:Last>Smeets</b:Last>
                        <b:First>Paul</b:First>
                    </b:Person>
                </b:NameList>
            </b:Author>
        </b:Author>
        <b:Pages>2505–2550</b:Pages>
        <b:JournalName>The Journal of Finance</b:JournalName>
        <b:Number>6</b:Number>
    </b:Source>
    <b:Source>
        <b:Year>2016</b:Year>
        <b:BIBTEX_Entry>article</b:BIBTEX_Entry>
        <b:SourceType>JournalArticle</b:SourceType>
        <b:Title>SRI funds: Investor demand, exogenous shocks and ESG profiles</b:Title>
        <b:Tag>bialkowski2016</b:Tag>
        <b:Publisher>University of Canterbury. Department of Economics and Finance</b:Publisher>
        <b:Author>
            <b:Author>
                <b:NameList>
                    <b:Person>
                        <b:Last>Bialkowski</b:Last>
                        <b:First>Jedrzej</b:First>
                    </b:Person>
                    <b:Person>
                        <b:Last>Starks</b:Last>
                        <b:Middle>T.</b:Middle>
                        <b:First>Laura</b:First>
                    </b:Person>
                </b:NameList>
            </b:Author>
        </b:Author>
    </b:Source>
    <b:Source>
        <b:Year>2014</b:Year>
        <b:Volume>60</b:Volume>
        <b:BIBTEX_Entry>article</b:BIBTEX_Entry>
        <b:SourceType>JournalArticle</b:SourceType>
        <b:Title>Environmental externalities and cost of capital</b:Title>
        <b:Tag>chava2014</b:Tag>
        <b:Publisher>INFORMS</b:Publisher>
        <b:Author>
            <b:Author>
                <b:NameList>
                    <b:Person>
                        <b:Last>Chava</b:Last>
                        <b:First>Sudheer</b:First>
                    </b:Person>
                </b:NameList>
            </b:Author>
        </b:Author>
        <b:Pages>2223–2247</b:Pages>
        <b:JournalName>Management Science</b:JournalName>
        <b:Number>9</b:Number>
    </b:Source>
    <b:Source>
        <b:Year>2001</b:Year>
        <b:Volume>36</b:Volume>
        <b:BIBTEX_Entry>article</b:BIBTEX_Entry>
        <b:SourceType>JournalArticle</b:SourceType>
        <b:Title>The effect of green investment on corporate behavior</b:Title>
        <b:Tag>heinkel2001</b:Tag>
        <b:Publisher>Cambridge University Press</b:Publisher>
        <b:Author>
            <b:Author>
                <b:NameList>
                    <b:Person>
                        <b:Last>Heinkel</b:Last>
                        <b:First>Robert</b:First>
                    </b:Person>
                    <b:Person>
                        <b:Last>Kraus</b:Last>
                        <b:First>Alan</b:First>
                    </b:Person>
                    <b:Person>
                        <b:Last>Zechner</b:Last>
                        <b:First>Josef</b:First>
                    </b:Person>
                </b:NameList>
            </b:Author>
        </b:Author>
        <b:Pages>431–449</b:Pages>
        <b:JournalName>Journal of financial and quantitative analysis</b:JournalName>
        <b:Number>4</b:Number>
    </b:Source>
    <b:Source>
        <b:Year>2010</b:Year>
        <b:Volume>77</b:Volume>
        <b:BIBTEX_Entry>article</b:BIBTEX_Entry>
        <b:SourceType>JournalArticle</b:SourceType>
        <b:Title>Individual and corporate social responsibility</b:Title>
        <b:Tag>benabou2010</b:Tag>
        <b:Publisher>Wiley Online Library</b:Publisher>
        <b:Author>
            <b:Author>
                <b:NameList>
                    <b:Person>
                        <b:Last>Bénabou</b:Last>
                        <b:First>Roland</b:First>
                    </b:Person>
                    <b:Person>
                        <b:Last>Tirole</b:Last>
                        <b:First>Jean</b:First>
                    </b:Person>
                </b:NameList>
            </b:Author>
        </b:Author>
        <b:Pages>1–19</b:Pages>
        <b:JournalName>Economica</b:JournalName>
        <b:Number>305</b:Number>
    </b:Source>
    <b:Source>
        <b:Year>2020</b:Year>
        <b:BIBTEX_Entry>article</b:BIBTEX_Entry>
        <b:SourceType>JournalArticle</b:SourceType>
        <b:Title>Which Investors Matter for Equity Valuations and Expected Returns?</b:Title>
        <b:Tag>koijen2020</b:Tag>
        <b:Author>
            <b:Author>
                <b:NameList>
                    <b:Person>
                        <b:Last>Koijen</b:Last>
                        <b:Middle>S. J.</b:Middle>
                        <b:First>Ralph</b:First>
                    </b:Person>
                    <b:Person>
                        <b:Last>Richmond</b:Last>
                        <b:Middle>J.</b:Middle>
                        <b:First>Robert</b:First>
                    </b:Person>
                    <b:Person>
                        <b:Last>Yogo</b:Last>
                        <b:First>Motohiro</b:First>
                    </b:Person>
                </b:NameList>
            </b:Author>
        </b:Author>
        <b:JournalName>NBER Working Paper</b:JournalName>
    </b:Source>
    <b:Source>
        <b:Year>2009</b:Year>
        <b:Volume>93</b:Volume>
        <b:BIBTEX_Entry>article</b:BIBTEX_Entry>
        <b:SourceType>JournalArticle</b:SourceType>
        <b:Title>The price of sin: The effects of social norms on markets</b:Title>
        <b:Tag>hong2009</b:Tag>
        <b:Publisher>Elsevier</b:Publisher>
        <b:Author>
            <b:Author>
                <b:NameList>
                    <b:Person>
                        <b:Last>Hong</b:Last>
                        <b:First>Harrison</b:First>
                    </b:Person>
                    <b:Person>
                        <b:Last>Kacperczyk</b:Last>
                        <b:First>Marcin</b:First>
                    </b:Person>
                </b:NameList>
            </b:Author>
        </b:Author>
        <b:Pages>15–36</b:Pages>
        <b:JournalName>Journal of Financial Economics</b:JournalName>
        <b:Number>1</b:Number>
    </b:Source>
    <b:Source>
        <b:Year>2014</b:Year>
        <b:BIBTEX_Entry>article</b:BIBTEX_Entry>
        <b:SourceType>JournalArticle</b:SourceType>
        <b:Title>The" Washing Machine": Investment Strategies and Corporate Behavior with Socially Responsible Investors</b:Title>
        <b:Tag>gollier2014</b:Tag>
        <b:Publisher>TSE Working Paper</b:Publisher>
        <b:Author>
            <b:Author>
                <b:NameList>
                    <b:Person>
                        <b:Last>Gollier</b:Last>
                        <b:First>Christian</b:First>
                    </b:Person>
                    <b:Person>
                        <b:Last>Pouget</b:Last>
                        <b:First>Sébastien</b:First>
                    </b:Person>
                </b:NameList>
            </b:Author>
        </b:Author>
    </b:Source>
    <b:Source>
        <b:Year>2020</b:Year>
        <b:BIBTEX_Entry>article</b:BIBTEX_Entry>
        <b:SourceType>JournalArticle</b:SourceType>
        <b:Title>Skills and Sentiment in Sustainable Investing</b:Title>
        <b:Author>
            <b:Author>
                <b:NameList>
                    <b:Person>
                        <b:Last>Brøgger</b:Last>
                        <b:Middle>Christian Svane</b:Middle>
                        <b:First>Andreas</b:First>
                    </b:Person>
                    <b:Person>
                        <b:Last>Kronies</b:Last>
                        <b:First>Alexander</b:First>
                    </b:Person>
                </b:NameList>
            </b:Author>
        </b:Author>
        <b:JournalName>Working Paper</b:JournalName>
    </b:Source>
    <b:Source>
        <b:Year>2018</b:Year>
        <b:BIBTEX_Entry>article</b:BIBTEX_Entry>
        <b:SourceType>JournalArticle</b:SourceType>
        <b:Title>Is socially responsible investing a luxury good?</b:Title>
        <b:Tag>bansal2018</b:Tag>
        <b:Author>
            <b:Author>
                <b:NameList>
                    <b:Person>
                        <b:Last>Bansal</b:Last>
                        <b:First>Ravi</b:First>
                    </b:Person>
                    <b:Person>
                        <b:Last>Wu</b:Last>
                        <b:Middle>Andrew</b:Middle>
                        <b:First>Di</b:First>
                    </b:Person>
                    <b:Person>
                        <b:Last>Yaron</b:Last>
                        <b:First>Amir</b:First>
                    </b:Person>
                </b:NameList>
            </b:Author>
        </b:Author>
        <b:JournalName>Available at SSRN 3259209</b:JournalName>
    </b:Source>
    <b:Source>
        <b:Year>2005</b:Year>
        <b:Volume>48</b:Volume>
        <b:BIBTEX_Entry>article</b:BIBTEX_Entry>
        <b:SourceType>JournalArticle</b:SourceType>
        <b:Title>The Reputational Penalties for Environmental Violations: Empirical Evidence</b:Title>
        <b:Tag>karpoff2005</b:Tag>
        <b:Publisher>[The University of Chicago Press, The Booth School of Business, University of Chicago, The University of Chicago Law School]</b:Publisher>
        <b:BIBTEX_Abstract>Abstract This paper examines the sizes of the fines, damage awards, remediation costs, and market value losses imposed on companies that violate environmental regulations. Firms that violate environmental laws suffer statistically significant losses in the market value of firm equity. The losses, however, are of similar magnitudes to the legal penalties imposed, and in the cross section, the market value loss is related to the size of the legal penalty. Thus, environmental violations are disciplined largely through legal and regulatory penalties, not through reputational penalties.</b:BIBTEX_Abstract>
        <b:URL>http://www.jstor.org/stable/10.1086/430806</b:URL>
        <b:Author>
            <b:Author>
                <b:NameList>
                    <b:Person>
                        <b:Last>Karpoff</b:Last>
                        <b:First>Jonathan M.</b:First>
                    </b:Person>
                    <b:Person>
                        <b:Last>John R. Lott</b:Last>
                        <b:First> Jr.</b:First>
                    </b:Person>
                    <b:Person>
                        <b:Last>Wehrly</b:Last>
                        <b:First>Eric W.</b:First>
                    </b:Person>
                </b:NameList>
            </b:Author>
        </b:Author>
        <b:Pages>653–675</b:Pages>
        <b:JournalName>The Journal of Law &amp; Economics</b:JournalName>
        <b:Number>2</b:Number>
        <b:StandardNumber> ISSN: 00222186, 15375285</b:StandardNumber>
    </b:Source>
    <b:Source>
        <b:Year>2020</b:Year>
        <b:Volume>33</b:Volume>
        <b:BIBTEX_Entry>article</b:BIBTEX_Entry>
        <b:SourceType>JournalArticle</b:SourceType>
        <b:Title>The importance of climate risks for institutional investors</b:Title>
        <b:Tag>krueger2020importance</b:Tag>
        <b:Publisher>Oxford University Press</b:Publisher>
        <b:Author>
            <b:Author>
                <b:NameList>
                    <b:Person>
                        <b:Last>Krueger</b:Last>
                        <b:First>Philipp</b:First>
                    </b:Person>
                    <b:Person>
                        <b:Last>Sautner</b:Last>
                        <b:First>Zacharias</b:First>
                    </b:Person>
                    <b:Person>
                        <b:Last>Starks</b:Last>
                        <b:Middle>T.</b:Middle>
                        <b:First>Laura</b:First>
                    </b:Person>
                </b:NameList>
            </b:Author>
        </b:Author>
        <b:Pages>1067–1111</b:Pages>
        <b:JournalName>The Review of Financial Studies</b:JournalName>
        <b:Number>3</b:Number>
    </b:Source>
    <b:Source>
        <b:Year>2020</b:Year>
        <b:BIBTEX_Entry>article</b:BIBTEX_Entry>
        <b:SourceType>JournalArticle</b:SourceType>
        <b:Title>Analyzing Active Managers' Commitment to ESG: Evidence from United Nations Principles for Responsible Investment</b:Title>
        <b:Tag>kim2020</b:Tag>
        <b:Author>
            <b:Author>
                <b:NameList>
                    <b:Person>
                        <b:Last>Kim</b:Last>
                        <b:First>Soohun</b:First>
                    </b:Person>
                    <b:Person>
                        <b:Last>Yoon</b:Last>
                        <b:First>Aaron</b:First>
                    </b:Person>
                </b:NameList>
            </b:Author>
        </b:Author>
        <b:JournalName>Available at SSRN</b:JournalName>
    </b:Source>
    <b:Source>
        <b:Year>2016</b:Year>
        <b:Volume>37</b:Volume>
        <b:BIBTEX_Entry>article</b:BIBTEX_Entry>
        <b:SourceType>JournalArticle</b:SourceType>
        <b:Title>Revisiting the corporate social performance-financial performance link: A replication of W addock and G raves</b:Title>
        <b:Tag>zhao2016</b:Tag>
        <b:Publisher>Wiley Online Library</b:Publisher>
        <b:Author>
            <b:Author>
                <b:NameList>
                    <b:Person>
                        <b:Last>Zhao</b:Last>
                        <b:First>Xiaoping</b:First>
                    </b:Person>
                    <b:Person>
                        <b:Last>Murrell</b:Last>
                        <b:Middle>J.</b:Middle>
                        <b:First>Audrey</b:First>
                    </b:Person>
                </b:NameList>
            </b:Author>
        </b:Author>
        <b:Pages>2378–2388</b:Pages>
        <b:JournalName>Strategic Management Journal</b:JournalName>
        <b:Number>11</b:Number>
    </b:Source>
    <b:Source>
        <b:Year>2003</b:Year>
        <b:Volume>118</b:Volume>
        <b:BIBTEX_Entry>article</b:BIBTEX_Entry>
        <b:SourceType>JournalArticle</b:SourceType>
        <b:Title>Corporate governance and equity prices</b:Title>
        <b:Tag>gompers2003</b:Tag>
        <b:Publisher>Oxford University Press</b:Publisher>
        <b:Author>
            <b:Author>
                <b:NameList>
                    <b:Person>
                        <b:Last>Gompers</b:Last>
                        <b:First>Paul</b:First>
                    </b:Person>
                    <b:Person>
                        <b:Last>Ishii</b:Last>
                        <b:First>Joy</b:First>
                    </b:Person>
                    <b:Person>
                        <b:Last>Metrick</b:Last>
                        <b:First>Andrew</b:First>
                    </b:Person>
                </b:NameList>
            </b:Author>
        </b:Author>
        <b:Pages>107–156</b:Pages>
        <b:JournalName>The quarterly journal of economics</b:JournalName>
        <b:Number>1</b:Number>
    </b:Source>
    <b:Source>
        <b:Year>2020</b:Year>
        <b:BIBTEX_Entry>article</b:BIBTEX_Entry>
        <b:SourceType>JournalArticle</b:SourceType>
        <b:Title>Carbon tail risk</b:Title>
        <b:Tag>ilhan2020</b:Tag>
        <b:Author>
            <b:Author>
                <b:NameList>
                    <b:Person>
                        <b:Last>Ilhan</b:Last>
                        <b:First>Emirhan</b:First>
                    </b:Person>
                    <b:Person>
                        <b:Last>Sautner</b:Last>
                        <b:First>Zacharias</b:First>
                    </b:Person>
                    <b:Person>
                        <b:Last>Vilkov</b:Last>
                        <b:First>Grigory</b:First>
                    </b:Person>
                </b:NameList>
            </b:Author>
        </b:Author>
        <b:JournalName>Review of Financial Studies, forthcoming</b:JournalName>
    </b:Source>
    <b:Source>
        <b:Year>2019</b:Year>
        <b:Volume>127</b:Volume>
        <b:BIBTEX_Entry>article</b:BIBTEX_Entry>
        <b:SourceType>JournalArticle</b:SourceType>
        <b:Title>A demand system approach to asset pricing</b:Title>
        <b:Tag>koijen2019</b:Tag>
        <b:Publisher>The University of Chicago Press Chicago, IL</b:Publisher>
        <b:Author>
            <b:Author>
                <b:NameList>
                    <b:Person>
                        <b:Last>Koijen</b:Last>
                        <b:Middle>S. J.</b:Middle>
                        <b:First>Ralph</b:First>
                    </b:Person>
                    <b:Person>
                        <b:Last>Yogo</b:Last>
                        <b:First>Motohiro</b:First>
                    </b:Person>
                </b:NameList>
            </b:Author>
        </b:Author>
        <b:Pages>1475–1515</b:Pages>
        <b:JournalName>Journal of Political Economy</b:JournalName>
        <b:Number>4</b:Number>
    </b:Source>
    <b:Source>
        <b:Year>2020</b:Year>
        <b:BIBTEX_Entry>article</b:BIBTEX_Entry>
        <b:SourceType>JournalArticle</b:SourceType>
        <b:Title>Love in the Time of COVID-19: The Resiliency of Environmental and Social Stocks</b:Title>
        <b:Tag>albuquerque2020</b:Tag>
        <b:Author>
            <b:Author>
                <b:NameList>
                    <b:Person>
                        <b:Last>Albuquerque</b:Last>
                        <b:First>Rui</b:First>
                    </b:Person>
                    <b:Person>
                        <b:Last>Koskinen</b:Last>
                        <b:First>Yrjo</b:First>
                    </b:Person>
                    <b:Person>
                        <b:Last>Yang</b:Last>
                        <b:First>Shuai</b:First>
                    </b:Person>
                    <b:Person>
                        <b:Last>Zhang</b:Last>
                        <b:First>Chendi</b:First>
                    </b:Person>
                </b:NameList>
            </b:Author>
        </b:Author>
        <b:Month>4</b:Month>
        <b:JournalName>CEPR Covid Economics, Vetted and Real-Time Papers</b:JournalName>
    </b:Source>
    <b:Source>
        <b:Year>2020</b:Year>
        <b:BIBTEX_Entry>article</b:BIBTEX_Entry>
        <b:SourceType>JournalArticle</b:SourceType>
        <b:Title>Socially responsible corporate customers</b:Title>
        <b:Tag>dai2020</b:Tag>
        <b:Publisher>Elsevier</b:Publisher>
        <b:Author>
            <b:Author>
                <b:NameList>
                    <b:Person>
                        <b:Last>Dai</b:Last>
                        <b:First>Rui</b:First>
                    </b:Person>
                    <b:Person>
                        <b:Last>Liang</b:Last>
                        <b:First>Hao</b:First>
                    </b:Person>
                    <b:Person>
                        <b:Last>Ng</b:Last>
                        <b:First>Lilian</b:First>
                    </b:Person>
                </b:NameList>
            </b:Author>
        </b:Author>
        <b:JournalName>Journal of Financial Economics</b:JournalName>
    </b:Source>
    <b:Source>
        <b:Year>2018</b:Year>
        <b:BIBTEX_Entry>article</b:BIBTEX_Entry>
        <b:SourceType>JournalArticle</b:SourceType>
        <b:Title>Financing the Response to Climate Change: The Pricing and Ownership of US Green Bonds</b:Title>
        <b:Tag>baker2018</b:Tag>
        <b:Author>
            <b:Author>
                <b:NameList>
                    <b:Person>
                        <b:Last>Baker</b:Last>
                        <b:First>Malcolm</b:First>
                    </b:Person>
                    <b:Person>
                        <b:Last>Bergstresser</b:Last>
                        <b:First>Daniel</b:First>
                    </b:Person>
                    <b:Person>
                        <b:Last>Serafeim</b:Last>
                        <b:First>George</b:First>
                    </b:Person>
                    <b:Person>
                        <b:Last>Wurgler</b:Last>
                        <b:First>Jeffrey</b:First>
                    </b:Person>
                </b:NameList>
            </b:Author>
        </b:Author>
        <b:JournalName>NBER Working Paper</b:JournalName>
    </b:Source>
    <b:Source>
        <b:Year>2020</b:Year>
        <b:BIBTEX_Entry>article</b:BIBTEX_Entry>
        <b:SourceType>JournalArticle</b:SourceType>
        <b:Title>Valuing ESG: Doing Good or Sounding Good?</b:Title>
        <b:Tag>cornell2020</b:Tag>
        <b:Author>
            <b:Author>
                <b:NameList>
                    <b:Person>
                        <b:Last>Cornell</b:Last>
                        <b:First>Bradford</b:First>
                    </b:Person>
                    <b:Person>
                        <b:Last>Damodaran</b:Last>
                        <b:First>Aswath</b:First>
                    </b:Person>
                </b:NameList>
            </b:Author>
        </b:Author>
        <b:JournalName>Available at SSRN 3557432</b:JournalName>
    </b:Source>
    <b:Source>
        <b:Year>2007</b:Year>
        <b:Volume>45</b:Volume>
        <b:BIBTEX_Entry>article</b:BIBTEX_Entry>
        <b:SourceType>JournalArticle</b:SourceType>
        <b:Title>A review of the Stern review on the economics of climate change</b:Title>
        <b:Tag>nordhaus2007review</b:Tag>
        <b:Author>
            <b:Author>
                <b:NameList>
                    <b:Person>
                        <b:Last>Nordhaus</b:Last>
                        <b:Middle>D.</b:Middle>
                        <b:First>William</b:First>
                    </b:Person>
                </b:NameList>
            </b:Author>
        </b:Author>
        <b:Pages>686–702</b:Pages>
        <b:JournalName>Journal of economic literature</b:JournalName>
        <b:Number>3</b:Number>
    </b:Source>
    <b:Source>
        <b:Year>2012</b:Year>
        <b:Volume>41</b:Volume>
        <b:BIBTEX_Entry>article</b:BIBTEX_Entry>
        <b:SourceType>JournalArticle</b:SourceType>
        <b:Title>The impact of corporate social performance on financial risk and utility: A longitudinal analysis</b:Title>
        <b:Tag>oikonomou2012</b:Tag>
        <b:Publisher>Wiley Online Library</b:Publisher>
        <b:Author>
            <b:Author>
                <b:NameList>
                    <b:Person>
                        <b:Last>Oikonomou</b:Last>
                        <b:First>Ioannis</b:First>
                    </b:Person>
                    <b:Person>
                        <b:Last>Brooks</b:Last>
                        <b:First>Chris</b:First>
                    </b:Person>
                    <b:Person>
                        <b:Last>Pavelin</b:Last>
                        <b:First>Stephen</b:First>
                    </b:Person>
                </b:NameList>
            </b:Author>
        </b:Author>
        <b:Pages>483–515</b:Pages>
        <b:JournalName>Financial Management</b:JournalName>
        <b:Number>2</b:Number>
    </b:Source>
    <b:Source>
        <b:Year>2019</b:Year>
        <b:BIBTEX_Entry>article</b:BIBTEX_Entry>
        <b:SourceType>JournalArticle</b:SourceType>
        <b:Title>(In)-Credibly Green: Which Bonds Trade at a Green Bond Premium?</b:Title>
        <b:Tag>kapraun2019</b:Tag>
        <b:Author>
            <b:Author>
                <b:NameList>
                    <b:Person>
                        <b:Last>Kapraun</b:Last>
                        <b:First>Julia</b:First>
                    </b:Person>
                    <b:Person>
                        <b:Last>Scheins</b:Last>
                        <b:First>Christopher</b:First>
                    </b:Person>
                </b:NameList>
            </b:Author>
        </b:Author>
        <b:JournalName>Available at SSRN 3347337</b:JournalName>
    </b:Source>
    <b:Source>
        <b:Year>2020</b:Year>
        <b:BIBTEX_Entry>article</b:BIBTEX_Entry>
        <b:SourceType>JournalArticle</b:SourceType>
        <b:Title>Environmental Impact Investing</b:Title>
        <b:Tag>deangelis2020</b:Tag>
        <b:Author>
            <b:Author>
                <b:NameList>
                    <b:Person>
                        <b:Last>De Angelis</b:Last>
                        <b:First>Tiziano</b:First>
                    </b:Person>
                    <b:Person>
                        <b:Last>Tankov</b:Last>
                        <b:First>Peter</b:First>
                    </b:Person>
                    <b:Person>
                        <b:Last>Zerbib</b:Last>
                        <b:Middle>David</b:Middle>
                        <b:First>Olivier</b:First>
                    </b:Person>
                </b:NameList>
            </b:Author>
        </b:Author>
        <b:JournalName>Available at SSRN 3562534</b:JournalName>
    </b:Source>
    <b:Source>
        <b:Year>2020</b:Year>
        <b:BIBTEX_Entry>article</b:BIBTEX_Entry>
        <b:SourceType>JournalArticle</b:SourceType>
        <b:Title>Being stranded with Fossil Fuel Reserves? Climate policy risk and the pricing of bank loans</b:Title>
        <b:Tag>delis2020</b:Tag>
        <b:Author>
            <b:Author>
                <b:NameList>
                    <b:Person>
                        <b:Last>de Greiff</b:Last>
                        <b:First>Kathrin</b:First>
                    </b:Person>
                    <b:Person>
                        <b:Last>Delis</b:Last>
                        <b:Middle>D.</b:Middle>
                        <b:First>Manthos</b:First>
                    </b:Person>
                    <b:Person>
                        <b:Last>Ongena</b:Last>
                        <b:First>Steven</b:First>
                    </b:Person>
                </b:NameList>
            </b:Author>
        </b:Author>
        <b:JournalName>Climate Policy Risk and the Pricing of Bank Loans (May 2018). CEPR Discussion Paper No. DP12928</b:JournalName>
    </b:Source>
    <b:Source>
        <b:Year>2015</b:Year>
        <b:Volume>61</b:Volume>
        <b:BIBTEX_Entry>article</b:BIBTEX_Entry>
        <b:SourceType>JournalArticle</b:SourceType>
        <b:Title>Does Corporate Social Responsibility Lead to Superior Financial Performance? A Regression Discontinuity Approach</b:Title>
        <b:Tag>flammer2015</b:Tag>
        <b:BIBTEX_Abstract>This study examines the effect of shareholder proposals related to corporate social responsibility (CSR) on financial performance. Specifically, I focus on CSR proposals that pass or fail by a small margin of votes. The passage of such “close call” proposals is akin to a random assignment of CSR to companies and hence provides a quasi-experiment to study the effect of CSR on performance. I find that the adoption of close call CSR proposals leads to positive announcement returns and superior accounting performance, implying that these proposals are value enhancing. When I examine the channels through which companies benefit from CSR, I find that labor productivity and sales growth increase after the vote. Finally, I document that close call CSR proposals differ from non-close proposals along several dimensions. Accordingly, although my results imply that adopting close call CSR proposals is beneficial to companies, they do not necessarily imply that CSR proposals are beneficial in general. Data, as supplemental material, are available at http://dx.doi.org/10.1287/mnsc.2014.2038. This paper was accepted by Wei Jiang, finance.</b:BIBTEX_Abstract>
        <b:URL>https://doi.org/10.1287/mnsc.2014.2038</b:URL>
        <b:DOI>10.1287/mnsc.2014.2038</b:DOI>
        <b:Author>
            <b:Author>
                <b:NameList>
                    <b:Person>
                        <b:Last>Flammer</b:Last>
                        <b:First>Caroline</b:First>
                    </b:Person>
                </b:NameList>
            </b:Author>
        </b:Author>
        <b:Pages>2549-2568</b:Pages>
        <b:JournalName>Management Science</b:JournalName>
        <b:Number>11</b:Number>
    </b:Source>
    <b:Source>
        <b:Year>2019</b:Year>
        <b:BIBTEX_Entry>article</b:BIBTEX_Entry>
        <b:SourceType>JournalArticle</b:SourceType>
        <b:Title>Responsible investing: The ESG-efficient frontier</b:Title>
        <b:Tag>pedersen2019</b:Tag>
        <b:Author>
            <b:Author>
                <b:NameList>
                    <b:Person>
                        <b:Last>Pedersen</b:Last>
                        <b:Middle>Heje</b:Middle>
                        <b:First>Lasse</b:First>
                    </b:Person>
                    <b:Person>
                        <b:Last>Fitzgibbons</b:Last>
                        <b:First>Shaun</b:First>
                    </b:Person>
                    <b:Person>
                        <b:Last>Pomorski</b:Last>
                        <b:First>Lukasz</b:First>
                    </b:Person>
                </b:NameList>
            </b:Author>
        </b:Author>
        <b:JournalName>Available at SSRN 3466417</b:JournalName>
    </b:Source>
    <b:Source>
        <b:Year>2014</b:Year>
        <b:Volume>35</b:Volume>
        <b:BIBTEX_Entry>article</b:BIBTEX_Entry>
        <b:SourceType>JournalArticle</b:SourceType>
        <b:Title>Corporate social responsibility and access to finance</b:Title>
        <b:Tag>cheng2014</b:Tag>
        <b:Publisher>Wiley Online Library</b:Publisher>
        <b:Author>
            <b:Author>
                <b:NameList>
                    <b:Person>
                        <b:Last>Cheng</b:Last>
                        <b:First>Beiting</b:First>
                    </b:Person>
                    <b:Person>
                        <b:Last>Ioannou</b:Last>
                        <b:First>Ioannis</b:First>
                    </b:Person>
                    <b:Person>
                        <b:Last>Serafeim</b:Last>
                        <b:First>George</b:First>
                    </b:Person>
                </b:NameList>
            </b:Author>
        </b:Author>
        <b:Pages>1–23</b:Pages>
        <b:JournalName>Strategic management journal</b:JournalName>
        <b:Number>1</b:Number>
    </b:Source>
    <b:Source>
        <b:Year>2018</b:Year>
        <b:BIBTEX_Entry>article</b:BIBTEX_Entry>
        <b:SourceType>JournalArticle</b:SourceType>
        <b:Title>Attention to Global Warming</b:Title>
        <b:Tag>choi2018attention</b:Tag>
        <b:Author>
            <b:Author>
                <b:NameList>
                    <b:Person>
                        <b:Last>Choi</b:Last>
                        <b:First>Darwin</b:First>
                    </b:Person>
                    <b:Person>
                        <b:Last>Gao</b:Last>
                        <b:First>Zhenyu</b:First>
                    </b:Person>
                    <b:Person>
                        <b:Last>Jiang</b:Last>
                        <b:First>Wenxi</b:First>
                    </b:Person>
                </b:NameList>
            </b:Author>
        </b:Author>
        <b:JournalName>Working Paper</b:JournalName>
    </b:Source>
    <b:Source>
        <b:LCID>1033</b:LCID>
        <b:Year>2011</b:Year>
        <b:Volume>20</b:Volume>
        <b:BIBTEX_Entry>article</b:BIBTEX_Entry>
        <b:Comments>Appeared earlier as CentER Discussion Paper 2006-09</b:Comments>
        <b:SourceType>JournalArticle</b:SourceType>
        <b:Title>Is ethical money financially smart? Nonfinancial attributes and money flows of socially responsible investment funds</b:Title>
        <b:Tag>renneboog</b:Tag>
        <b:Publisher>Academic Press Inc.</b:Publisher>
        <b:BIBTEX_Abstract>We study the money flows into and out of socially responsible investment (SRI) funds around the world. In their investment decisions, investors in SRI funds may be more concerned with ethical or social issues than with fund performance. Therefore, SRI money flows are less related to past fund returns. Ethical money is less sensitive to past negative returns than are conventional fund flows, especially when SRI funds primarily use negative or Sin/Ethical screens. Social attributes of SRI funds weaken the relation between money inflows and past positive returns. However, money flows into funds with environmental screens are more sensitive to past positive returns than are conventional fund flows. Stock picking based on in-house SRI research increases the money flows. These results give evidence on the role of nonfinancial attributes, which induce heterogeneity of investor clienteles within SRI funds. We find no evidence of a smart money effect, as the funds that receive more inflows neither outperform nor underperform their benchmarks or conventional funds.</b:BIBTEX_Abstract>
        <b:DOI>10.1016/j.jfi.2010.12.003</b:DOI>
        <b:Author>
            <b:Author>
                <b:NameList>
                    <b:Person>
                        <b:Last>Renneboog</b:Last>
                        <b:Middle>D. R.</b:Middle>
                        <b:First>L.</b:First>
                    </b:Person>
                    <b:Person>
                        <b:Last>Ter Horst</b:Last>
                        <b:Middle>R.</b:Middle>
                        <b:First>J.</b:First>
                    </b:Person>
                    <b:Person>
                        <b:Last>Zhang</b:Last>
                        <b:First>C.</b:First>
                    </b:Person>
                </b:NameList>
            </b:Author>
        </b:Author>
        <b:Pages>562–588</b:Pages>
        <b:JournalName>Journal of Financial Intermediation</b:JournalName>
        <b:Number>4</b:Number>
        <b:StandardNumber> ISSN: 1042-9573</b:StandardNumber>
    </b:Source>
    <b:Source>
        <b:Year>2017</b:Year>
        <b:BIBTEX_Entry>article</b:BIBTEX_Entry>
        <b:SourceType>JournalArticle</b:SourceType>
        <b:Title>Evolution of Assessments of the Economics of Global Warming: Changes in the DICE model, 1992–2017</b:Title>
        <b:Tag>nordhaus2017evolution</b:Tag>
        <b:Author>
            <b:Author>
                <b:NameList>
                    <b:Person>
                        <b:Last>Nordhaus</b:Last>
                        <b:Middle>D.</b:Middle>
                        <b:First>William</b:First>
                    </b:Person>
                </b:NameList>
            </b:Author>
        </b:Author>
        <b:JournalName>NBER Working Paper</b:JournalName>
    </b:Source>
    <b:Source>
        <b:Year>2013</b:Year>
        <b:Volume>108</b:Volume>
        <b:BIBTEX_Entry>article</b:BIBTEX_Entry>
        <b:SourceType>JournalArticle</b:SourceType>
        <b:Title>Learning and the disappearing association between governance and returns</b:Title>
        <b:Tag>bebchuk2013</b:Tag>
        <b:Publisher>Elsevier</b:Publisher>
        <b:Author>
            <b:Author>
                <b:NameList>
                    <b:Person>
                        <b:Last>Bebchuk</b:Last>
                        <b:Middle>A.</b:Middle>
                        <b:First>Lucian</b:First>
                    </b:Person>
                    <b:Person>
                        <b:Last>Cohen</b:Last>
                        <b:First>Alma</b:First>
                    </b:Person>
                    <b:Person>
                        <b:Last>Wang</b:Last>
                        <b:Middle>C. Y.</b:Middle>
                        <b:First>Charles</b:First>
                    </b:Person>
                </b:NameList>
            </b:Author>
        </b:Author>
        <b:Pages>323–348</b:Pages>
        <b:JournalName>Journal of financial economics</b:JournalName>
        <b:Number>2</b:Number>
    </b:Source>
    <b:Source>
        <b:Year>2016</b:Year>
        <b:Volume>71</b:Volume>
        <b:BIBTEX_Entry>article</b:BIBTEX_Entry>
        <b:SourceType>JournalArticle</b:SourceType>
        <b:Title>The Price of Political Uncertainty: Theory and Evidence from the Option Market</b:Title>
        <b:Tag>kelly2016</b:Tag>
        <b:BIBTEX_Abstract>ABSTRACT We empirically analyze the pricing of political uncertainty, guided by a theoretical model of government policy choice. To isolate political uncertainty, we exploit its variation around national elections and global summits. We find that political uncertainty is priced in the equity option market as predicted by theory. Options whose lives span political events tend to be more expensive. Such options provide valuable protection against the price, variance, and tail risks associated with political events. This protection is more valuable in a weaker economy and amid higher political uncertainty. The effects of political uncertainty spill over across countries.</b:BIBTEX_Abstract>
        <b:Author>
            <b:Author>
                <b:NameList>
                    <b:Person>
                        <b:Last>Kelly</b:Last>
                        <b:First>Bryan</b:First>
                    </b:Person>
                    <b:Person>
                        <b:Last>Pastor</b:Last>
                        <b:First>Lubos</b:First>
                    </b:Person>
                    <b:Person>
                        <b:Last>Veronesi</b:Last>
                        <b:First>Pietro</b:First>
                    </b:Person>
                </b:NameList>
            </b:Author>
        </b:Author>
        <b:Pages>2417-2480</b:Pages>
        <b:JournalName>The Journal of Finance</b:JournalName>
        <b:Number>5</b:Number>
    </b:Source>
    <b:Source>
        <b:Year>2015</b:Year>
        <b:Volume>115</b:Volume>
        <b:BIBTEX_Entry>article</b:BIBTEX_Entry>
        <b:SourceType>JournalArticle</b:SourceType>
        <b:Title>Corporate goodness and shareholder wealth</b:Title>
        <b:Tag>kruger2015</b:Tag>
        <b:Publisher>Elsevier</b:Publisher>
        <b:Author>
            <b:Author>
                <b:NameList>
                    <b:Person>
                        <b:Last>Krüger</b:Last>
                        <b:First>Philipp</b:First>
                    </b:Person>
                </b:NameList>
            </b:Author>
        </b:Author>
        <b:Pages>304–329</b:Pages>
        <b:JournalName>Journal of financial economics</b:JournalName>
        <b:Number>2</b:Number>
    </b:Source>
    <b:Source>
        <b:Year>2017</b:Year>
        <b:Volume>72</b:Volume>
        <b:BIBTEX_Entry>article</b:BIBTEX_Entry>
        <b:SourceType>JournalArticle</b:SourceType>
        <b:Title>Social capital, trust, and firm performance: The value of corporate social responsibility during the financial crisis</b:Title>
        <b:Tag>lins2017</b:Tag>
        <b:Publisher>Wiley Online Library</b:Publisher>
        <b:Author>
            <b:Author>
                <b:NameList>
                    <b:Person>
                        <b:Last>Lins</b:Last>
                        <b:Middle>V.</b:Middle>
                        <b:First>Karl</b:First>
                    </b:Person>
                    <b:Person>
                        <b:Last>Servaes</b:Last>
                        <b:First>Henri</b:First>
                    </b:Person>
                    <b:Person>
                        <b:Last>Tamayo</b:Last>
                        <b:First>Ane</b:First>
                    </b:Person>
                </b:NameList>
            </b:Author>
        </b:Author>
        <b:Pages>1785–1824</b:Pages>
        <b:JournalName>The Journal of Finance</b:JournalName>
        <b:Number>4</b:Number>
    </b:Source>
    <b:Source>
        <b:Year>1987</b:Year>
        <b:Volume>42</b:Volume>
        <b:BIBTEX_Entry>article</b:BIBTEX_Entry>
        <b:SourceType>JournalArticle</b:SourceType>
        <b:Title>A Simple Model of Capital Market Equilibrium with Incomplete Information</b:Title>
        <b:Tag>merton</b:Tag>
        <b:Author>
            <b:Author>
                <b:NameList>
                    <b:Person>
                        <b:Last>Merton</b:Last>
                        <b:Middle>C.</b:Middle>
                        <b:First>Robert</b:First>
                    </b:Person>
                </b:NameList>
            </b:Author>
        </b:Author>
        <b:Pages>483-510</b:Pages>
        <b:JournalName>The Journal of Finance</b:JournalName>
        <b:Number>3</b:Number>
    </b:Source>
    <b:Source>
        <b:Year>2020</b:Year>
        <b:BIBTEX_Entry>article</b:BIBTEX_Entry>
        <b:SourceType>JournalArticle</b:SourceType>
        <b:Title>ESG Investing: How to Optimize Impact?</b:Title>
        <b:Tag>landier2020</b:Tag>
        <b:Author>
            <b:Author>
                <b:NameList>
                    <b:Person>
                        <b:Last>Landier</b:Last>
                        <b:First>Augustin</b:First>
                    </b:Person>
                    <b:Person>
                        <b:Last>Lovo</b:Last>
                        <b:First>Stefano</b:First>
                    </b:Person>
                </b:NameList>
            </b:Author>
        </b:Author>
        <b:JournalName>HEC Paris Research Paper No. FIN-2020-1363</b:JournalName>
    </b:Source>
    <b:Source>
        <b:Year>2020</b:Year>
        <b:Volume>135</b:Volume>
        <b:BIBTEX_Entry>article</b:BIBTEX_Entry>
        <b:SourceType>JournalArticle</b:SourceType>
        <b:Title>An inconvenient cost: The effects of climate change on municipal bonds</b:Title>
        <b:Tag>painter2020</b:Tag>
        <b:Publisher>Elsevier</b:Publisher>
        <b:Author>
            <b:Author>
                <b:NameList>
                    <b:Person>
                        <b:Last>Painter</b:Last>
                        <b:First>Marcus</b:First>
                    </b:Person>
                </b:NameList>
            </b:Author>
        </b:Author>
        <b:Pages>468–482</b:Pages>
        <b:JournalName>Journal of Financial Economics</b:JournalName>
        <b:Number>2</b:Number>
    </b:Source>
    <b:Source>
        <b:Year>2018</b:Year>
        <b:BIBTEX_Entry>article</b:BIBTEX_Entry>
        <b:SourceType>JournalArticle</b:SourceType>
        <b:Title>Corporate governance and pollution externalities of public and private firms</b:Title>
        <b:Tag>corpgov2018</b:Tag>
        <b:Author>
            <b:Author>
                <b:NameList>
                    <b:Person>
                        <b:Last>Forster</b:Last>
                        <b:First>Margaret</b:First>
                    </b:Person>
                    <b:Person>
                        <b:Last>Shive</b:Last>
                        <b:First>Sophie</b:First>
                    </b:Person>
                </b:NameList>
            </b:Author>
        </b:Author>
        <b:JournalName>Working Paper</b:JournalName>
    </b:Source>
    <b:Source>
        <b:LCID>1033</b:LCID>
        <b:Year>2019</b:Year>
        <b:Volume>65</b:Volume>
        <b:BIBTEX_Entry>article</b:BIBTEX_Entry>
        <b:Comments>Copyright - Copyright Institute for Operations Research and the Management Sciences Dec 2019; Ultimo aggiornamento - 2020-03-25</b:Comments>
        <b:SourceType>JournalArticle</b:SourceType>
        <b:Title>Peer Effects of Corporate Social Responsibility</b:Title>
        <b:Tag>rohtua</b:Tag>
        <b:BIBTEX_Abstract>We investigate how firms react to their product-market peers' commitment to and adoption of corporate social responsibility (CSR) using a regression discontinuity design approach. Relying on the passage or failure of CSR proposals by a narrow margin of votes during shareholder meetings, we find the passage of a close-call CSR proposal and its implementation are followed by the adoption of similar CSR practices by peer firms. In addition, peers that have greater difficulty in catching up with the voting firm in CSR experience significantly lower stock returns around the passage, consistent with the notion that the spillover effect of the adoption of CSR is a strategic response to competitive threat. Using alternative definitions of peers and examining underlying mechanisms, we further rule out alternative explanations, such as that based on propagation by financial intermediaries.</b:BIBTEX_Abstract>
        <b:BIBTEX_KeyWords>Business And Economics–Labor And Industrial Relations; Social responsibility; Proposals; Strategic planning; Corporate governance; Catching; Discontinuity; Voting</b:BIBTEX_KeyWords>
        <b:URL>http://proxy.library.nyu.edu/login?url=https://search-proquest-com.proxy.library.nyu.edu/docview/2325279603?accountid=12768</b:URL>
        <b:Author>
            <b:Author>
                <b:NameList>
                    <b:Person>
                        <b:Last>Cao</b:Last>
                        <b:First>Jie</b:First>
                    </b:Person>
                    <b:Person>
                        <b:Last>Liang</b:Last>
                        <b:First>Hao</b:First>
                    </b:Person>
                    <b:Person>
                        <b:Last>Zhan</b:Last>
                        <b:First>Xintong</b:First>
                    </b:Person>
                </b:NameList>
            </b:Author>
        </b:Author>
        <b:Pages>5487</b:Pages>
        <b:Month>12</b:Month>
        <b:JournalName>Management Science</b:JournalName>
        <b:Number>12</b:Number>
        <b:StandardNumber> ISBN: 00251909</b:StandardNumber>
    </b:Source>
    <b:Source>
        <b:Year>2007</b:Year>
        <b:BIBTEX_Entry>book</b:BIBTEX_Entry>
        <b:SourceType>Book</b:SourceType>
        <b:Title>The Economics of Climate Change, the Stern Review.</b:Title>
        <b:Tag>sternreview</b:Tag>
        <b:Publisher>Cambridge University Press</b:Publisher>
        <b:Author>
            <b:Author>
                <b:NameList>
                    <b:Person>
                        <b:Last>Stern</b:Last>
                        <b:First>Nicholas</b:First>
                    </b:Person>
                </b:NameList>
            </b:Author>
        </b:Author>
    </b:Source>
    <b:Source>
        <b:Year>2020</b:Year>
        <b:BIBTEX_Entry>article</b:BIBTEX_Entry>
        <b:SourceType>JournalArticle</b:SourceType>
        <b:Title>Is Sustainable Investing Driven by Altruism: Evidence from Shocks to Philanthropy</b:Title>
        <b:Tag>boutchkova2020</b:Tag>
        <b:Author>
            <b:Author>
                <b:NameList>
                    <b:Person>
                        <b:Last>Boutchkova</b:Last>
                        <b:First>Maria</b:First>
                    </b:Person>
                    <b:Person>
                        <b:Last>Gonzalez</b:Last>
                        <b:First>Angelica</b:First>
                    </b:Person>
                    <b:Person>
                        <b:Last>Zhang</b:Last>
                        <b:First>Renfang</b:First>
                    </b:Person>
                </b:NameList>
            </b:Author>
        </b:Author>
        <b:JournalName>Available at SSRN</b:JournalName>
    </b:Source>
    <b:Source>
        <b:Year>2020</b:Year>
        <b:BIBTEX_Entry>article</b:BIBTEX_Entry>
        <b:SourceType>JournalArticle</b:SourceType>
        <b:Title>A Sustainable Capital Asset Pricing Model (S-CAPM): Evidence from green investing and sin stock exclusion</b:Title>
        <b:Tag>zerbib2020</b:Tag>
        <b:Author>
            <b:Author>
                <b:NameList>
                    <b:Person>
                        <b:Last>Zerbib</b:Last>
                        <b:Middle>David</b:Middle>
                        <b:First>Olivier</b:First>
                    </b:Person>
                </b:NameList>
            </b:Author>
        </b:Author>
        <b:JournalName>Available at SSRN 3455090</b:JournalName>
    </b:Source>
    <b:Source>
        <b:Year>2019</b:Year>
        <b:BIBTEX_Entry>article</b:BIBTEX_Entry>
        <b:SourceType>JournalArticle</b:SourceType>
        <b:Title>Impact investing</b:Title>
        <b:Tag>barber2019</b:Tag>
        <b:Author>
            <b:Author>
                <b:NameList>
                    <b:Person>
                        <b:Last>Barber</b:Last>
                        <b:Middle>M.</b:Middle>
                        <b:First>Brad</b:First>
                    </b:Person>
                    <b:Person>
                        <b:Last>Morse</b:Last>
                        <b:First>Adair</b:First>
                    </b:Person>
                    <b:Person>
                        <b:Last>Yasuda</b:Last>
                        <b:First>Ayako</b:First>
                    </b:Person>
                </b:NameList>
            </b:Author>
        </b:Author>
        <b:JournalName>NBER Working Paper</b:JournalName>
    </b:Source>
    <b:Source>
        <b:Year>2020</b:Year>
        <b:BIBTEX_Entry>article</b:BIBTEX_Entry>
        <b:SourceType>JournalArticle</b:SourceType>
        <b:Title>Sustainable Investing in Equilibrium</b:Title>
        <b:Tag>pastor2020</b:Tag>
        <b:Author>
            <b:Author>
                <b:NameList>
                    <b:Person>
                        <b:Last>Pastor</b:Last>
                        <b:First>Lubos</b:First>
                    </b:Person>
                    <b:Person>
                        <b:Last>Stambaugh</b:Last>
                        <b:Middle>F.</b:Middle>
                        <b:First>Robert</b:First>
                    </b:Person>
                    <b:Person>
                        <b:Last>Taylor</b:Last>
                        <b:Middle>A.</b:Middle>
                        <b:First>Lucian</b:First>
                    </b:Person>
                </b:NameList>
            </b:Author>
        </b:Author>
        <b:JournalName>NBER Working Paper</b:JournalName>
    </b:Source>
    <b:Source>
        <b:Year>2019</b:Year>
        <b:Volume>74</b:Volume>
        <b:BIBTEX_Entry>article</b:BIBTEX_Entry>
        <b:SourceType>JournalArticle</b:SourceType>
        <b:Title>Do investors value sustainability? A natural experiment examining ranking and fund flows</b:Title>
        <b:Tag>hartzmark2019</b:Tag>
        <b:Publisher>Wiley Online Library</b:Publisher>
        <b:Author>
            <b:Author>
                <b:NameList>
                    <b:Person>
                        <b:Last>Hartzmark</b:Last>
                        <b:Middle>M.</b:Middle>
                        <b:First>Samuel</b:First>
                    </b:Person>
                    <b:Person>
                        <b:Last>Sussman</b:Last>
                        <b:Middle>B.</b:Middle>
                        <b:First>Abigail</b:First>
                    </b:Person>
                </b:NameList>
            </b:Author>
        </b:Author>
        <b:Pages>2789–2837</b:Pages>
        <b:JournalName>The Journal of Finance</b:JournalName>
        <b:Number>6</b:Number>
    </b:Source>
    <b:Source>
        <b:Year>2019</b:Year>
        <b:Volume>131</b:Volume>
        <b:BIBTEX_Entry>article</b:BIBTEX_Entry>
        <b:SourceType>JournalArticle</b:SourceType>
        <b:Title>Do institutional investors drive corporate social responsibility? International evidence</b:Title>
        <b:Tag>dyck2019</b:Tag>
        <b:Publisher>Elsevier</b:Publisher>
        <b:Author>
            <b:Author>
                <b:NameList>
                    <b:Person>
                        <b:Last>Dyck</b:Last>
                        <b:First>Alexander</b:First>
                    </b:Person>
                    <b:Person>
                        <b:Last>Lins</b:Last>
                        <b:Middle>V.</b:Middle>
                        <b:First>Karl</b:First>
                    </b:Person>
                    <b:Person>
                        <b:Last>Roth</b:Last>
                        <b:First>Lukas</b:First>
                    </b:Person>
                    <b:Person>
                        <b:Last>Wagner</b:Last>
                        <b:Middle>F.</b:Middle>
                        <b:First>Hannes</b:First>
                    </b:Person>
                </b:NameList>
            </b:Author>
        </b:Author>
        <b:Pages>693–714</b:Pages>
        <b:JournalName>Journal of Financial Economics</b:JournalName>
        <b:Number>3</b:Number>
    </b:Source>
    <b:Source>
        <b:Year>2009</b:Year>
        <b:BIBTEX_Entry>article</b:BIBTEX_Entry>
        <b:SourceType>JournalArticle</b:SourceType>
        <b:Title>Does it pay to be good... and does it matter? A meta-analysis of the relationship between corporate social and financial performance</b:Title>
        <b:Tag>margolis2009</b:Tag>
        <b:Author>
            <b:Author>
                <b:NameList>
                    <b:Person>
                        <b:Last>Margolis</b:Last>
                        <b:Middle>D.</b:Middle>
                        <b:First>Joshua</b:First>
                    </b:Person>
                    <b:Person>
                        <b:Last>Elfenbein</b:Last>
                        <b:Middle>Anger</b:Middle>
                        <b:First>Hillary</b:First>
                    </b:Person>
                    <b:Person>
                        <b:Last>Walsh</b:Last>
                        <b:Middle>P.</b:Middle>
                        <b:First>James</b:First>
                    </b:Person>
                </b:NameList>
            </b:Author>
        </b:Author>
        <b:JournalName>And does it matter</b:JournalName>
    </b:Source>
    <b:Source>
        <b:Year>2016</b:Year>
        <b:Volume>43</b:Volume>
        <b:BIBTEX_Entry>article</b:BIBTEX_Entry>
        <b:SourceType>JournalArticle</b:SourceType>
        <b:Title>The effects of corporate and country sustainability characteristics on the cost of debt: An international investigation</b:Title>
        <b:Tag>hoepner2016</b:Tag>
        <b:Publisher>Wiley Online Library</b:Publisher>
        <b:Author>
            <b:Author>
                <b:NameList>
                    <b:Person>
                        <b:Last>Hoepner</b:Last>
                        <b:First>Andreas</b:First>
                    </b:Person>
                    <b:Person>
                        <b:Last>Oikonomou</b:Last>
                        <b:First>Ioannis</b:First>
                    </b:Person>
                    <b:Person>
                        <b:Last>Scholtens</b:Last>
                        <b:First>Bert</b:First>
                    </b:Person>
                    <b:Person>
                        <b:Last>Schröder</b:Last>
                        <b:First>Michael</b:First>
                    </b:Person>
                </b:NameList>
            </b:Author>
        </b:Author>
        <b:Pages>158–190</b:Pages>
        <b:JournalName>Journal of Business Finance &amp; Accounting</b:JournalName>
        <b:Number>1-2</b:Number>
    </b:Source>
    <b:Source>
        <b:Year>1994</b:Year>
        <b:Volume>31</b:Volume>
        <b:BIBTEX_Entry>book</b:BIBTEX_Entry>
        <b:SourceType>Book</b:SourceType>
        <b:Title>Managing the global commons: the economics of climate change</b:Title>
        <b:Tag>nordhaus1994book</b:Tag>
        <b:Publisher>MIT press Cambridge, MA</b:Publisher>
        <b:Author>
            <b:Author>
                <b:NameList>
                    <b:Person>
                        <b:Last>Nordhaus</b:Last>
                        <b:Middle>D.</b:Middle>
                        <b:First>William</b:First>
                    </b:Person>
                </b:NameList>
            </b:Author>
        </b:Author>
    </b:Source>
    <b:Source>
        <b:Year>1997</b:Year>
        <b:Volume>18</b:Volume>
        <b:BIBTEX_Entry>article</b:BIBTEX_Entry>
        <b:SourceType>JournalArticle</b:SourceType>
        <b:Title>The Corporate Social Performance-Financial Performance Link</b:Title>
        <b:Tag>waddock1997</b:Tag>
        <b:Publisher>Wiley</b:Publisher>
        <b:BIBTEX_Abstract>Strategic managers are consistently faced with the decision of how to allocate scarce corporate resources in an environment that is placing more and more pressures on them. Recent scholarship in strategic management suggests that many of these pressures come directly from sources associated with social issues in management, rather than traditional arenas of strategic management. Using a greatly improved source of data on corporate social performance, this paper reports the results of a rigorous study of the empirical linkages between financial and social performance. Corporate social performance (CSP) is found to be positively associated with prior financial performance, supporting the theory that slack resource availability and CSP are positively related. CSP is also found to be positively associated with future financial performance, supporting the theory that good management and CSP are positively related.</b:BIBTEX_Abstract>
        <b:URL>http://www.jstor.org/stable/3088143</b:URL>
        <b:Author>
            <b:Author>
                <b:NameList>
                    <b:Person>
                        <b:Last>Waddock</b:Last>
                        <b:Middle>A.</b:Middle>
                        <b:First>Sandra</b:First>
                    </b:Person>
                    <b:Person>
                        <b:Last>Graves</b:Last>
                        <b:Middle>B.</b:Middle>
                        <b:First>Samuel</b:First>
                    </b:Person>
                </b:NameList>
            </b:Author>
        </b:Author>
        <b:Pages>303–319</b:Pages>
        <b:JournalName>Strategic Management Journal</b:JournalName>
        <b:Number>4</b:Number>
        <b:StandardNumber> ISSN: 01432095, 10970266</b:StandardNumber>
    </b:Source>
    <b:Source>
        <b:Year>2018</b:Year>
        <b:BIBTEX_Entry>article</b:BIBTEX_Entry>
        <b:SourceType>JournalArticle</b:SourceType>
        <b:Title>Climate change and long-run discount rates: Evidence from real estate</b:Title>
        <b:Tag>stroebel2018discount</b:Tag>
        <b:Author>
            <b:Author>
                <b:NameList>
                    <b:Person>
                        <b:Last>Giglio</b:Last>
                        <b:First>Stefano</b:First>
                    </b:Person>
                    <b:Person>
                        <b:Last>Maggiori</b:Last>
                        <b:First>Matteo</b:First>
                    </b:Person>
                    <b:Person>
                        <b:Last>Rao</b:Last>
                        <b:First>Krishna</b:First>
                    </b:Person>
                    <b:Person>
                        <b:Last>Stroebel</b:Last>
                        <b:First>Johannes</b:First>
                    </b:Person>
                    <b:Person>
                        <b:Last>Weber</b:Last>
                        <b:First>Andreas</b:First>
                    </b:Person>
                </b:NameList>
            </b:Author>
        </b:Author>
        <b:JournalName>R &amp; R Journal of Political Economy</b:JournalName>
    </b:Source>
    <b:Source>
        <b:Year>2020</b:Year>
        <b:BIBTEX_Entry>article</b:BIBTEX_Entry>
        <b:SourceType>JournalArticle</b:SourceType>
        <b:Title>Aggregate confusion: the divergence of ESG ratings</b:Title>
        <b:Tag>berg2020</b:Tag>
        <b:Author>
            <b:Author>
                <b:NameList>
                    <b:Person>
                        <b:Last>Berg</b:Last>
                        <b:First>Florian</b:First>
                    </b:Person>
                    <b:Person>
                        <b:Last>Koelbel</b:Last>
                        <b:Middle>F.</b:Middle>
                        <b:First>Julian</b:First>
                    </b:Person>
                    <b:Person>
                        <b:Last>Rigobon</b:Last>
                        <b:First>Roberto</b:First>
                    </b:Person>
                </b:NameList>
            </b:Author>
        </b:Author>
        <b:JournalName>Available at SSRN 3438533</b:JournalName>
    </b:Source>
    <b:Source>
        <b:Year>2014</b:Year>
        <b:Volume>130</b:Volume>
        <b:BIBTEX_Entry>article</b:BIBTEX_Entry>
        <b:SourceType>JournalArticle</b:SourceType>
        <b:Title>Very long-run discount rates</b:Title>
        <b:Tag>stroebel2014qje</b:Tag>
        <b:Publisher>MIT Press</b:Publisher>
        <b:Author>
            <b:Author>
                <b:NameList>
                    <b:Person>
                        <b:Last>Giglio</b:Last>
                        <b:First>Stefano</b:First>
                    </b:Person>
                    <b:Person>
                        <b:Last>Maggiori</b:Last>
                        <b:First>Matteo</b:First>
                    </b:Person>
                    <b:Person>
                        <b:Last>Stroebel</b:Last>
                        <b:First>Johannes</b:First>
                    </b:Person>
                </b:NameList>
            </b:Author>
        </b:Author>
        <b:Pages>1–53</b:Pages>
        <b:JournalName>The Quarterly Journal of Economics</b:JournalName>
        <b:Number>1</b:Number>
    </b:Source>
    <b:Source>
        <b:Year>2019</b:Year>
        <b:Volume>65</b:Volume>
        <b:BIBTEX_Entry>article</b:BIBTEX_Entry>
        <b:SourceType>JournalArticle</b:SourceType>
        <b:Title>Corporate social responsibility and firm risk: Theory and empirical evidence</b:Title>
        <b:Tag>albuquerque2019</b:Tag>
        <b:Publisher>INFORMS</b:Publisher>
        <b:Author>
            <b:Author>
                <b:NameList>
                    <b:Person>
                        <b:Last>Albuquerque</b:Last>
                        <b:First>Rui</b:First>
                    </b:Person>
                    <b:Person>
                        <b:Last>Koskinen</b:Last>
                        <b:First>Yrjö</b:First>
                    </b:Person>
                    <b:Person>
                        <b:Last>Zhang</b:Last>
                        <b:First>Chendi</b:First>
                    </b:Person>
                </b:NameList>
            </b:Author>
        </b:Author>
        <b:Pages>4451–4469</b:Pages>
        <b:JournalName>Management Science</b:JournalName>
        <b:Number>10</b:Number>
    </b:Source>
    <b:Source>
        <b:Year>2020</b:Year>
        <b:Volume>33</b:Volume>
        <b:BIBTEX_Entry>article</b:BIBTEX_Entry>
        <b:SourceType>JournalArticle</b:SourceType>
        <b:Title>Does climate change affect real estate prices? Only if you believe in it</b:Title>
        <b:Tag>baldauf2020</b:Tag>
        <b:Publisher>Oxford University Press</b:Publisher>
        <b:Author>
            <b:Author>
                <b:NameList>
                    <b:Person>
                        <b:Last>Baldauf</b:Last>
                        <b:First>Markus</b:First>
                    </b:Person>
                    <b:Person>
                        <b:Last>Garlappi</b:Last>
                        <b:First>Lorenzo</b:First>
                    </b:Person>
                    <b:Person>
                        <b:Last>Yannelis</b:Last>
                        <b:First>Constantine</b:First>
                    </b:Person>
                </b:NameList>
            </b:Author>
        </b:Author>
        <b:Pages>1256–1295</b:Pages>
        <b:JournalName>The Review of Financial Studies</b:JournalName>
        <b:Number>3</b:Number>
    </b:Source>
    <b:Source>
        <b:Year>2013</b:Year>
        <b:Volume>56</b:Volume>
        <b:BIBTEX_Entry>article</b:BIBTEX_Entry>
        <b:SourceType>JournalArticle</b:SourceType>
        <b:Title>Corporate Social Responsibility and Shareholder Reaction: The Environmental Awareness of Investors</b:Title>
        <b:Tag>flammer2013</b:Tag>
        <b:BIBTEX_Abstract>This study examines whether shareholders are sensitive to corporations' environmental footprint. Specifically, I conduct an event study around the announcement of corporate news related to environment for all US publicly traded companies from 1980 to 2009. In keeping with the view that environmental corporate social responsibility (CSR) generates new and competitive resources for firms, I find that companies reported to behave responsibly toward the environment experience a significant stock price increase, whereas firms that behave irresponsibly face a significant decrease. Extending this view of “environment-as-a-resource,” I posit that the value of environmental CSR depends on external and internal moderators. First, I argue that external pressure to behave responsibly towards the environment―which has increased dramatically over recent decades―exacerbates the punishment for eco-harmful behavior and reduces the reward for eco-friendly initiatives. This argument is supported by the data: over time, the negative stock market reaction to eco-harmful behavior has increased, while the positive reaction to eco-friendly initiatives has decreased. Second, I argue that environmental CSR is a resource with decreasing marginal returns and insurance-like features. In keeping with this view, I find that the positive (negative) stock market reaction to eco-friendly (-harmful) events is smaller for companies with higher levels of environmental CSR.</b:BIBTEX_Abstract>
        <b:URL>https://doi.org/10.5465/amj.2011.0744</b:URL>
        <b:DOI>10.5465/amj.2011.0744</b:DOI>
        <b:Author>
            <b:Author>
                <b:NameList>
                    <b:Person>
                        <b:Last>Flammer</b:Last>
                        <b:First>Caroline</b:First>
                    </b:Person>
                </b:NameList>
            </b:Author>
        </b:Author>
        <b:Pages>758-781</b:Pages>
        <b:JournalName>Academy of Management Journal</b:JournalName>
        <b:Number>3</b:Number>
    </b:Source>
    <b:Source>
        <b:Year>2018</b:Year>
        <b:BIBTEX_Entry>article</b:BIBTEX_Entry>
        <b:SourceType>JournalArticle</b:SourceType>
        <b:Title>ESG shareholder engagement and downside risk</b:Title>
        <b:Tag>hoepner2018</b:Tag>
        <b:Author>
            <b:Author>
                <b:NameList>
                    <b:Person>
                        <b:Last>Hoepner</b:Last>
                        <b:Middle>G. F.</b:Middle>
                        <b:First>Andreas</b:First>
                    </b:Person>
                    <b:Person>
                        <b:Last>Oikonomou</b:Last>
                        <b:First>Ioannis</b:First>
                    </b:Person>
                    <b:Person>
                        <b:Last>Sautner</b:Last>
                        <b:First>Zacharias</b:First>
                    </b:Person>
                    <b:Person>
                        <b:Last>Starks</b:Last>
                        <b:Middle>T.</b:Middle>
                        <b:First>Laura</b:First>
                    </b:Person>
                    <b:Person>
                        <b:Last>Zhou</b:Last>
                        <b:First>Xiaoyan</b:First>
                    </b:Person>
                </b:NameList>
            </b:Author>
        </b:Author>
        <b:JournalName>Working Paper</b:JournalName>
    </b:Source>
    <b:Source>
        <b:Year>2018</b:Year>
        <b:BIBTEX_Entry>article</b:BIBTEX_Entry>
        <b:SourceType>JournalArticle</b:SourceType>
        <b:Title>The sustainability footprint of institutional investors</b:Title>
        <b:Tag>gibson2018</b:Tag>
        <b:Author>
            <b:Author>
                <b:NameList>
                    <b:Person>
                        <b:Last>Gibson</b:Last>
                        <b:First>Rajna</b:First>
                    </b:Person>
                    <b:Person>
                        <b:Last>Krueger</b:Last>
                        <b:First>Philipp</b:First>
                    </b:Person>
                </b:NameList>
            </b:Author>
        </b:Author>
        <b:JournalName>Swiss Finance Institute Research Paper</b:JournalName>
        <b:Number>17-05</b:Number>
    </b:Source>
    <b:Source>
        <b:Year>2011</b:Year>
        <b:Volume>35</b:Volume>
        <b:BIBTEX_Entry>article</b:BIBTEX_Entry>
        <b:SourceType>JournalArticle</b:SourceType>
        <b:Title>The impact of corporate social responsibility on the cost of bank loans</b:Title>
        <b:Tag>goss2011</b:Tag>
        <b:BIBTEX_Abstract>This study examines the link between corporate social responsibility (CSR) and bank debt. Our focus on banks exploits their specialized role as delegated monitors of the firm. Using a sample of 3996 loans to US firms, we find that firms with social responsibility concerns pay between 7 and 18 basis points more than firms that are more responsible. Lenders are more sensitive to CSR concerns in the absence of security. We document a mixed reaction to discretionary CSR investments. Low-quality borrowers that engage in discretionary CSR spending face higher loan spreads and shorter maturities, but lenders are indifferent to CSR investments by high-quality borrowers.</b:BIBTEX_Abstract>
        <b:BIBTEX_KeyWords>Loan pricing, Corporate social responsibility, Socially responsible investing</b:BIBTEX_KeyWords>
        <b:URL>http://www.sciencedirect.com/science/article/pii/S0378426610004498</b:URL>
        <b:DOI>https://doi.org/10.1016/j.jbankfin.2010.12.002</b:DOI>
        <b:Author>
            <b:Author>
                <b:NameList>
                    <b:Person>
                        <b:Last>Goss</b:Last>
                        <b:First>Allen</b:First>
                    </b:Person>
                    <b:Person>
                        <b:Last>Roberts</b:Last>
                        <b:Middle>S.</b:Middle>
                        <b:First>Gordon</b:First>
                    </b:Person>
                </b:NameList>
            </b:Author>
        </b:Author>
        <b:Pages>1794-1810</b:Pages>
        <b:JournalName>Journal of Banking &amp; Finance</b:JournalName>
        <b:Number>7</b:Number>
        <b:StandardNumber> ISSN: 0378-4266</b:StandardNumber>
    </b:Source>
    <b:Source>
        <b:Year>2005</b:Year>
        <b:Volume>77</b:Volume>
        <b:BIBTEX_Entry>article</b:BIBTEX_Entry>
        <b:SourceType>JournalArticle</b:SourceType>
        <b:Title>Asset pricing with liquidity risk</b:Title>
        <b:Tag>acharya2005</b:Tag>
        <b:Publisher>Elsevier</b:Publisher>
        <b:Author>
            <b:Author>
                <b:NameList>
                    <b:Person>
                        <b:Last>Acharya</b:Last>
                        <b:Middle>V.</b:Middle>
                        <b:First>Viral</b:First>
                    </b:Person>
                    <b:Person>
                        <b:Last>Pedersen</b:Last>
                        <b:Middle>Heje</b:Middle>
                        <b:First>Lasse</b:First>
                    </b:Person>
                </b:NameList>
            </b:Author>
        </b:Author>
        <b:Pages>375–410</b:Pages>
        <b:JournalName>Journal of financial Economics</b:JournalName>
        <b:Number>2</b:Number>
    </b:Source>
    <b:Source>
        <b:Year>2015</b:Year>
        <b:Volume>35</b:Volume>
        <b:BIBTEX_Entry>article</b:BIBTEX_Entry>
        <b:SourceType>JournalArticle</b:SourceType>
        <b:Title>Stock market reaction to ESG-oriented management: An event study analysis on a disclosing policy in Japan</b:Title>
        <b:Tag>mitsuyama2015</b:Tag>
        <b:Author>
            <b:Author>
                <b:NameList>
                    <b:Person>
                        <b:Last>Mitsuyama</b:Last>
                        <b:First>N.</b:First>
                    </b:Person>
                    <b:Person>
                        <b:Last>Shimizutani</b:Last>
                        <b:First>Satoshi</b:First>
                    </b:Person>
                </b:NameList>
            </b:Author>
        </b:Author>
        <b:Pages>1098-1108</b:Pages>
        <b:Month>1</b:Month>
        <b:JournalName>Economics Bulletin</b:JournalName>
    </b:Source>
    <b:Source>
        <b:Year>2018</b:Year>
        <b:BIBTEX_Entry>article</b:BIBTEX_Entry>
        <b:SourceType>JournalArticle</b:SourceType>
        <b:Title>Temperature Shocks and Earnings News</b:Title>
        <b:Tag>addoum2018</b:Tag>
        <b:Author>
            <b:Author>
                <b:NameList>
                    <b:Person>
                        <b:Last>Addoum</b:Last>
                        <b:Middle>M.</b:Middle>
                        <b:First>Jawad</b:First>
                    </b:Person>
                    <b:Person>
                        <b:Last>Ng</b:Last>
                        <b:Middle>T.</b:Middle>
                        <b:First>David</b:First>
                    </b:Person>
                    <b:Person>
                        <b:Last>Ortiz-Bobea</b:Last>
                        <b:First>Ariel</b:First>
                    </b:Person>
                </b:NameList>
            </b:Author>
        </b:Author>
        <b:JournalName>Working Paper</b:JournalName>
    </b:Source>
    <b:Source>
        <b:Year>2012</b:Year>
        <b:BIBTEX_Entry>techreport</b:BIBTEX_Entry>
        <b:SourceType>Report</b:SourceType>
        <b:Title>Financial constraints on corporate goodness</b:Title>
        <b:Tag>hong2012</b:Tag>
        <b:Author>
            <b:Author>
                <b:NameList>
                    <b:Person>
                        <b:Last>Hong</b:Last>
                        <b:First>Harrison</b:First>
                    </b:Person>
                    <b:Person>
                        <b:Last>Kubik</b:Last>
                        <b:Middle>D.</b:Middle>
                        <b:First>Jeffrey</b:First>
                    </b:Person>
                    <b:Person>
                        <b:Last>Scheinkman</b:Last>
                        <b:Middle>A.</b:Middle>
                        <b:First>Jose</b:First>
                    </b:Person>
                </b:NameList>
            </b:Author>
        </b:Author>
        <b:JournalName>NBER Working Paper</b:JournalName>
        <b:ThesisType>Tech. rep.</b:ThesisType>
    </b:Source>
    <b:Source>
        <b:Year>2020</b:Year>
        <b:BIBTEX_Entry>article</b:BIBTEX_Entry>
        <b:SourceType>JournalArticle</b:SourceType>
        <b:Title>The Asymmetry in Responsible Investing Preferences</b:Title>
        <b:Tag>humphrey2020</b:Tag>
        <b:Author>
            <b:Author>
                <b:NameList>
                    <b:Person>
                        <b:Last>Humphrey</b:Last>
                        <b:First>Jacquelyn</b:First>
                    </b:Person>
                    <b:Person>
                        <b:Last>Kogan</b:Last>
                        <b:First>Shimon</b:First>
                    </b:Person>
                    <b:Person>
                        <b:Last>Sagi</b:Last>
                        <b:First>Jacob</b:First>
                    </b:Person>
                    <b:Person>
                        <b:Last>Starks</b:Last>
                        <b:Middle>T.</b:Middle>
                        <b:First>Laura</b:First>
                    </b:Person>
                </b:NameList>
            </b:Author>
        </b:Author>
        <b:JournalName>Working Paper</b:JournalName>
    </b:Source>
    <b:Source>
        <b:Year>2016</b:Year>
        <b:Volume>122</b:Volume>
        <b:BIBTEX_Entry>article</b:BIBTEX_Entry>
        <b:SourceType>JournalArticle</b:SourceType>
        <b:Title>Socially responsible firms</b:Title>
        <b:Tag>ferrell2016</b:Tag>
        <b:BIBTEX_Abstract>In the corporate finance tradition, starting with Berle and Means (1932), corporations should generally be run to maximize shareholder value. The agency view of corporate social responsibility (CSR) considers CSR an agency problem and a waste of corporate resources. Given our identification strategy by means of an instrumental variable approach, we find that well-governed firms that suffer less from agency concerns (less cash abundance, positive pay-for-performance, small control wedge, strong minority protection) engage more in CSR. We also find that a positive relation exists between CSR and value and that CSR attenuates the negative relation between managerial entrenchment and value.</b:BIBTEX_Abstract>
        <b:Author>
            <b:Author>
                <b:NameList>
                    <b:Person>
                        <b:Last>Ferrell</b:Last>
                        <b:First>Allen</b:First>
                    </b:Person>
                    <b:Person>
                        <b:Last>Liang</b:Last>
                        <b:First>Hao</b:First>
                    </b:Person>
                    <b:Person>
                        <b:Last>Renneboog</b:Last>
                        <b:First>Luc</b:First>
                    </b:Person>
                </b:NameList>
            </b:Author>
        </b:Author>
        <b:Pages>585-606</b:Pages>
        <b:JournalName>Journal of Financial Economics</b:JournalName>
        <b:Number>3</b:Number>
        <b:StandardNumber> ISSN: 0304-405X</b:StandardNumber>
    </b:Source>
    <b:Source>
        <b:Year>2020</b:Year>
        <b:BIBTEX_Entry>article</b:BIBTEX_Entry>
        <b:SourceType>JournalArticle</b:SourceType>
        <b:Title>Do investors care about carbon risk?</b:Title>
        <b:Tag>bolton2020</b:Tag>
        <b:Author>
            <b:Author>
                <b:NameList>
                    <b:Person>
                        <b:Last>Bolton</b:Last>
                        <b:First>Patrick</b:First>
                    </b:Person>
                    <b:Person>
                        <b:Last>Kacperczyk</b:Last>
                        <b:First>Marcin</b:First>
                    </b:Person>
                </b:NameList>
            </b:Author>
        </b:Author>
        <b:JournalName>NBER Working Paper</b:JournalName>
    </b:Source>
    <b:Source>
        <b:Year>2007</b:Year>
        <b:Volume>83</b:Volume>
        <b:BIBTEX_Entry>article</b:BIBTEX_Entry>
        <b:SourceType>JournalArticle</b:SourceType>
        <b:Title>Disagreement, tastes, and asset prices</b:Title>
        <b:Tag>ffrench</b:Tag>
        <b:Author>
            <b:Author>
                <b:NameList>
                    <b:Person>
                        <b:Last>Fama</b:Last>
                        <b:First>Eugene</b:First>
                    </b:Person>
                    <b:Person>
                        <b:Last>French</b:Last>
                        <b:First>Kenneth</b:First>
                    </b:Person>
                </b:NameList>
            </b:Author>
        </b:Author>
        <b:Pages>667-689</b:Pages>
        <b:JournalName>Journal of Financial Economics</b:JournalName>
    </b:Source>
    <b:Source>
        <b:Year>2018</b:Year>
        <b:Volume>74</b:Volume>
        <b:BIBTEX_Entry>article</b:BIBTEX_Entry>
        <b:SourceType>JournalArticle</b:SourceType>
        <b:Title>Why and how investors use ESG information: evidence from a global survey</b:Title>
        <b:Tag>amel2018a</b:Tag>
        <b:Publisher>Financial Analysts Journal</b:Publisher>
        <b:Author>
            <b:Author>
                <b:NameList>
                    <b:Person>
                        <b:Last>Amel-Zadeh</b:Last>
                        <b:First>A.</b:First>
                    </b:Person>
                    <b:Person>
                        <b:Last>Serafeim</b:Last>
                        <b:First>G.</b:First>
                    </b:Person>
                </b:NameList>
            </b:Author>
        </b:Author>
        <b:Pages>87-103</b:Pages>
        <b:JournalName>Financial Analysts Journal</b:JournalName>
        <b:Number>3</b:Number>
    </b:Source>
    <b:Source>
        <b:Year>1953</b:Year>
        <b:BIBTEX_Entry>book</b:BIBTEX_Entry>
        <b:SourceType>Book</b:SourceType>
        <b:Title>Social Responsibility of the Businessman.</b:Title>
        <b:Tag>bowen1953social</b:Tag>
        <b:Publisher>New York: Harper and Row</b:Publisher>
        <b:Author>
            <b:Author>
                <b:NameList>
                    <b:Person>
                        <b:Last>Bowen</b:Last>
                        <b:Middle>R.</b:Middle>
                        <b:First>Howard</b:First>
                    </b:Person>
                </b:NameList>
            </b:Author>
        </b:Author>
    </b:Source>
    <b:Source>
        <b:Year>2011</b:Year>
        <b:Volume>35</b:Volume>
        <b:BIBTEX_Entry>article</b:BIBTEX_Entry>
        <b:SourceType>JournalArticle</b:SourceType>
        <b:Title>Does corporate social responsibility affect the cost of capital?</b:Title>
        <b:Tag>elghoul2011</b:Tag>
        <b:Publisher>Elsevier</b:Publisher>
        <b:Author>
            <b:Author>
                <b:NameList>
                    <b:Person>
                        <b:Last>El Ghoul</b:Last>
                        <b:First>Sadok</b:First>
                    </b:Person>
                    <b:Person>
                        <b:Last>Guedhami</b:Last>
                        <b:First>Omrane</b:First>
                    </b:Person>
                    <b:Person>
                        <b:Last>Kwok</b:Last>
                        <b:Middle>C. Y.</b:Middle>
                        <b:First>Chuck</b:First>
                    </b:Person>
                    <b:Person>
                        <b:Last>Mishra</b:Last>
                        <b:Middle>R.</b:Middle>
                        <b:First>Dev</b:First>
                    </b:Person>
                </b:NameList>
            </b:Author>
        </b:Author>
        <b:Pages>2388–2406</b:Pages>
        <b:JournalName>Journal of Banking &amp; Finance</b:JournalName>
        <b:Number>9</b:Number>
    </b:Source>
    <b:Source>
        <b:Year>2017</b:Year>
        <b:Volume>52</b:Volume>
        <b:BIBTEX_Entry>article</b:BIBTEX_Entry>
        <b:SourceType>JournalArticle</b:SourceType>
        <b:Title>Social Screens and Systematic Investor Boycott Risk</b:Title>
        <b:Tag>luo2017</b:Tag>
        <b:Publisher>Cambridge University Press</b:Publisher>
        <b:DOI>10.1017/S0022109016000910</b:DOI>
        <b:Author>
            <b:Author>
                <b:NameList>
                    <b:Person>
                        <b:Last>Luo</b:Last>
                        <b:Middle>Arthur</b:Middle>
                        <b:First>H.</b:First>
                    </b:Person>
                    <b:Person>
                        <b:Last>Balvers</b:Last>
                        <b:Middle>J.</b:Middle>
                        <b:First>Ronald</b:First>
                    </b:Person>
                </b:NameList>
            </b:Author>
        </b:Author>
        <b:Pages>365–399</b:Pages>
        <b:JournalName>Journal of Financial and Quantitative Analysis</b:JournalName>
        <b:Number>1</b:Number>
    </b:Source>
    <b:Source>
        <b:Year>2019</b:Year>
        <b:BIBTEX_Entry>article</b:BIBTEX_Entry>
        <b:SourceType>JournalArticle</b:SourceType>
        <b:Title>Mortgage finance in the face of rising climate risk</b:Title>
        <b:Tag>ouazad2019</b:Tag>
        <b:Author>
            <b:Author>
                <b:NameList>
                    <b:Person>
                        <b:Last>Ouazad</b:Last>
                        <b:First>Amine</b:First>
                    </b:Person>
                    <b:Person>
                        <b:Last>Kahn</b:Last>
                        <b:Middle>E.</b:Middle>
                        <b:First>Matthew</b:First>
                    </b:Person>
                </b:NameList>
            </b:Author>
        </b:Author>
        <b:JournalName>NBER working paper</b:JournalName>
    </b:Source>
</b:Sources>
